tosa_adapter_model_explorer/__init__.py
tosa_adapter_model_explorer/builder.py
tosa_adapter_model_explorer/main.py
tosa_adapter_model_explorer/util.py
tosa_adapter_model_explorer/tests/__init__.py
tosa_adapter_model_explorer/tests/test_e2e.py
tosa_adapter_model_explorer/tests/test_model_explorer_cli.py
tosa_adapter_model_explorer/tosa_1_0/__init__.py
tosa_adapter_model_explorer/tosa_1_0/tosa_1_0_generated.py
tosa_adapter_model_explorer/tosa_1_0/tosa_1_0_generated.pyi
tosa_adapter_model_explorer-0.1.0.dist-info/licenses/LICENSE
tosa_adapter_model_explorer-0.1.0.dist-info/METADATA
tosa_adapter_model_explorer-0.1.0.dist-info/WHEEL
tosa_adapter_model_explorer-0.1.0.dist-info/top_level.txt
tosa_adapter_model_explorer-0.1.0.dist-info/RECORD
