Metadata-Version: 2.4
Name: tosa-adapter-model-explorer
Version: 0.1.0
Summary: Adapter for ai-edge-model-explorer to support TOSA files
License-Expression: Apache-2.0
Project-URL: Repository, https://github.com/arm/tosa-adapter-model-explorer
Keywords: model-explorer,tosa,visualization
Classifier: Development Status :: 4 - Beta
Classifier: Intended Audience :: Developers
Classifier: Operating System :: POSIX
Classifier: Programming Language :: Python :: 3.10
Classifier: Programming Language :: Python :: 3.11
Classifier: Programming Language :: Python :: 3.12
Requires-Python: <3.13,>=3.10
License-File: LICENSE
Requires-Dist: ai-edge-model-explorer<0.2.0,>=0.1.26
Requires-Dist: flatbuffers
Provides-Extra: test
Requires-Dist: pytest; extra == "test"
Requires-Dist: pytest-timeout; extra == "test"
Requires-Dist: ai-edge-model-explorer==0.1.28; extra == "test"
Provides-Extra: format
Requires-Dist: ruff==0.14.2; extra == "format"
Provides-Extra: coverage
Requires-Dist: pytest-cov; extra == "coverage"
Provides-Extra: build
Requires-Dist: build; extra == "build"
Dynamic: license-file
